bluefors_slave.py
bluefors_slave-1.0b3.dist-info/LICENSE
bluefors_slave-1.0b3.dist-info/METADATA
bluefors_slave-1.0b3.dist-info/WHEEL
bluefors_slave-1.0b3.dist-info/top_level.txt
bluefors_slave-1.0b3.dist-info/RECORD
